Metadata-Version: 2.1
Name: cinspector
Version: 0.0.1
Summary: A static C source code analysis framework
Home-page: https://github.com/PeiweiHu/cinspector
Author: Peiwei Hu
Author-email: jlu.hpw@foxmail.com
License: WTFPL
Classifier: Programming Language :: Python :: 3
Classifier: Operating System :: OS Independent
Requires-Python: >=3.6
License-File: LICENSE
